numba_cache_lock/__init__.py
numba_cache_lock-0.1.0a2.dist-info/LICENSE.md
numba_cache_lock-0.1.0a2.dist-info/METADATA
numba_cache_lock-0.1.0a2.dist-info/WHEEL
numba_cache_lock-0.1.0a2.dist-info/RECORD
