Metadata-Version: 2.3
Name: numba-cache-lock
Version: 0.1.0a2
Summary: A caching system for Numba with file locking support
Keywords: numba,caching
Author: Guilherme Leobas
Requires-Python: >=3.9
Classifier: License :: OSI Approved :: MIT License
Classifier: Operating System :: OS Independent
Classifier: Programming Language :: Python :: 3
Classifier: Programming Language :: Python :: 3.9
Classifier: Programming Language :: Python :: 3.10
Classifier: Programming Language :: Python :: 3.11
Classifier: Programming Language :: Python :: 3.12
Requires-Dist: flufl-lock (>=8.2.0,<9.0.0)
Requires-Dist: numba
Project-URL: Home, https://github.com/Quansight/numba-cache-lock
Project-URL: Source, https://github.com/Quansight/numba-cache-lock
